ipfnetcfgbu/__init__.py
ipfnetcfgbu/cli/__init__.py
ipfnetcfgbu/cli/backup.py
ipfnetcfgbu/cli/main.py
ipfnetcfgbu/cli/root.py
ipfnetcfgbu/cli/vcs.py
ipfnetcfgbu/config.py
ipfnetcfgbu/config_model.py
ipfnetcfgbu/consts.py
ipfnetcfgbu/domain_remover.py
ipfnetcfgbu/ipf.py
ipfnetcfgbu/logging.py
ipfnetcfgbu/vcs/__init__.py
ipfnetcfgbu/vcs/git.py
ipf_netcfgbu-1.0.0.dist-info/entry_points.txt
ipf_netcfgbu-1.0.0.dist-info/LICENSE
ipf_netcfgbu-1.0.0.dist-info/WHEEL
ipf_netcfgbu-1.0.0.dist-info/METADATA
ipf_netcfgbu-1.0.0.dist-info/RECORD
