Metadata-Version: 2.1
Name: ipf-netcfgbu
Version: 1.0.0
Summary: Network Config Backup from IP Fabric to Git
License: Apache-2.0
Author: Jeremy Schulman
Author-email: nwkautomaniac@gmail.com
Requires-Python: >=3.8.1,<4.0
Classifier: License :: OSI Approved :: Apache Software License
Classifier: Programming Language :: Python :: 3
Classifier: Programming Language :: Python :: 3.9
Classifier: Programming Language :: Python :: 3.10
Classifier: Programming Language :: Python :: 3.11
Requires-Dist: aio-ipfabric (>=1.0.0,<2.0.0)
Requires-Dist: aiofiles (>=22.1.0,<23.0.0)
Requires-Dist: click (>=8.1.3,<9.0.0)
Requires-Dist: first (>=2.0.2,<3.0.0)
Requires-Dist: maya (>=0.6.1,<0.7.0)
Requires-Dist: pexpect (>=4.8.0,<5.0.0)
Requires-Dist: pydantic (>=1.10.2,<2.0.0)
Requires-Dist: toml (>=0.10.2,<0.11.0)
